{"name":"Daily Life","slug":"Daily-Life","count":5,"postlist":[{"title":"VScode个性化","uid":"ca50d6c63c682d4350ca97cb9bed15aa","slug":"VScode个性化","date":"2025-03-22T07:28:30.000Z","updated":"2025-03-22T11:04:44.884Z","comments":true,"path":"api/articles/VScode个性化.json","keywords":null,"cover":"/img/vscode.jpg","text":"vscode优化使用体验篇（设置 | 插件） 众所周知，vscode是一个非常好用的文本编辑器，通过各式各样的插件几乎是万能的，也可以作为好用的IDE，但vsc...","permalink":"/post/VScode个性化","photos":[],"count_time":{"symbolsCount":"2.6k","symbolsTime":"2 mins."},"categories":[{"name":"VScode","slug":"VScode","count":1,"path":"api/categories/VScode.json"}],"tags":[{"name":"Study","slug":"Study","count":8,"path":"api/tags/Study.json"},{"name":"Daily Life","slug":"Daily-Life","count":5,"path":"api/tags/Daily-Life.json"}],"author":{"name":"Aurorp1g","slug":"blog-author","avatar":"/avatar.jpg","link":"/","description":"一枚热爱计算机的博主","socials":{"github":"https://github.com/Aurorp1g","twitter":"","stackoverflow":"","wechat":"","qq":"","weibo":"","zhihu":"","csdn":"","juejin":"","customs":{}}}},{"title":"Blog 主题更改","uid":"1828396dcb62aff8de00fb0b79b85c29","slug":"Blog-主题更改","date":"2025-03-12T06:22:33.000Z","updated":"2025-03-21T10:55:28.979Z","comments":true,"path":"api/articles/Blog-主题更改.json","keywords":null,"cover":"/img/Blog_theme_change.jpg","text":"今天我正式更改了Blog的主题，主要在颜色搭配和插件使用上做了调整。原来主题的颜色对我来说太过妖艳，所以我改成了更成熟稳重的配色，同时保留了赛博风格，这样更符合...","permalink":"/post/Blog-主题更改","photos":[],"count_time":{"symbolsCount":"1.1k","symbolsTime":"1 mins."},"categories":[{"name":"琐记","slug":"琐记","count":4,"path":"api/categories/琐记.json"}],"tags":[{"name":"Daily Life","slug":"Daily-Life","count":5,"path":"api/tags/Daily-Life.json"}],"author":{"name":"Aurorp1g","slug":"blog-author","avatar":"/avatar.jpg","link":"/","description":"一枚热爱计算机的博主","socials":{"github":"https://github.com/Aurorp1g","twitter":"","stackoverflow":"","wechat":"","qq":"","weibo":"","zhihu":"","csdn":"","juejin":"","customs":{}}},"feature":true},{"title":"RSA_factor_search","uid":"0bd558ed7d7fa7646fcd3ada2dcc8c3c","slug":"RSA-factor-search","date":"2025-03-09T13:46:04.000Z","updated":"2025-03-17T12:06:43.804Z","comments":true,"path":"api/articles/RSA-factor-search.json","keywords":null,"cover":"/img/RSA_factor_search.png","text":"随手记录一下我在两个星期前接到的一个项目，一个跟RSA因数分解有关的项目 这个项目涉及一个专利，在这里就不展示它的具体内容了 这个项目的大致内容是，使用专利中提...","permalink":"/post/RSA-factor-search","photos":[],"count_time":{"symbolsCount":"1.6k","symbolsTime":"1 mins."},"categories":[{"name":"琐记","slug":"琐记","count":4,"path":"api/categories/琐记.json"}],"tags":[{"name":"Daily Life","slug":"Daily-Life","count":5,"path":"api/tags/Daily-Life.json"}],"author":{"name":"Aurorp1g","slug":"blog-author","avatar":"/avatar.jpg","link":"/","description":"一枚热爱计算机的博主","socials":{"github":"https://github.com/Aurorp1g","twitter":"","stackoverflow":"","wechat":"","qq":"","weibo":"","zhihu":"","csdn":"","juejin":"","customs":{}}}},{"title":"My First Blog","uid":"3cec10ea82879603dbf419df4f15b5d8","slug":"My-First-Blog","date":"2025-03-03T12:30:18.000Z","updated":"2025-03-19T04:14:50.908Z","comments":true,"path":"api/articles/My-First-Blog.json","keywords":null,"cover":"/img/My_First_Blog.jpg","text":"今天写我的第一篇博客。这几天我在忙着将自己本地电脑上的项目通过git上传到github 记录一下我搭建在github上的一个项目：生日祝福网站代码。这是一个在其...","permalink":"/post/My-First-Blog","photos":[],"count_time":{"symbolsCount":780,"symbolsTime":"1 mins."},"categories":[{"name":"琐记","slug":"琐记","count":4,"path":"api/categories/琐记.json"}],"tags":[{"name":"Daily Life","slug":"Daily-Life","count":5,"path":"api/tags/Daily-Life.json"}],"author":{"name":"Aurorp1g","slug":"blog-author","avatar":"/avatar.jpg","link":"/","description":"一枚热爱计算机的博主","socials":{"github":"https://github.com/Aurorp1g","twitter":"","stackoverflow":"","wechat":"","qq":"","weibo":"","zhihu":"","csdn":"","juejin":"","customs":{}}},"feature":true},{"title":"Hello World","uid":"b9663f58f18133b35bfe243f3e916a80","slug":"hello-world","date":"2025-03-01T09:16:14.149Z","updated":"2025-03-17T12:04:28.566Z","comments":true,"path":"api/articles/hello-world.json","keywords":null,"cover":"/img/Hello_World.jpg","text":"随着自己学习计算机的内容越来越深入，枯燥无味的气息充斥了我的学习生活。 为了打破这种局面，我决定弄个博客来记录我的计算机学习生涯。 开始学习计算机的时间是在高中...","permalink":"/post/hello-world","photos":[],"count_time":{"symbolsCount":692,"symbolsTime":"1 mins."},"categories":[{"name":"琐记","slug":"琐记","count":4,"path":"api/categories/琐记.json"}],"tags":[{"name":"Daily Life","slug":"Daily-Life","count":5,"path":"api/tags/Daily-Life.json"}],"author":{"name":"Aurorp1g","slug":"blog-author","avatar":"/avatar.jpg","link":"/","description":"一枚热爱计算机的博主","socials":{"github":"https://github.com/Aurorp1g","twitter":"","stackoverflow":"","wechat":"","qq":"","weibo":"","zhihu":"","csdn":"","juejin":"","customs":{}}},"feature":true}]}